[
    {
        "@id": "https://openebench.bsc.es/monitor/metrics/bioconda:perl-extutils-cbuilder:0.280230/cmd/search.cpan.org",
        "@license": "https://creativecommons.org/licenses/by/4.0/",
        "@nmsp": "bioconda",
        "@timestamp": "2021-04-08T03:03:11.365417Z",
        "@type": "metrics",
        "distribution": {
            "packages": true,
            "sourcecode": {}
        },
        "project": {
            "build": {},
            "deployment": {},
            "license": {
                "open_source": false,
                "osi": false
            },
            "publications": [],
            "summary": {
                "description": true
            },
            "website": {
                "access_time": 1067,
                "bioschemas": false,
                "copyright": false,
                "half_year_stat": [
                    {
                        "days": 181,
                        "serie": [
                            181
                        ],
                        "status": 200
                    }
                ],
                "https": true,
                "last_check": "2021-04-08T03:03:11.315526Z",
                "last_month_access": {
                    "average_access_time": 1899,
                    "downtime_days": 0,
                    "uptime_days": 30
                },
                "license": false,
                "operational": 200,
                "redirects": [
                    {
                        "status": 301,
                        "url": "https://metacpan.org/release/ExtUtils-CBuilder"
                    }
                ],
                "ssl": true,
                "ssl_err": null
            }
        }
    },
    {
        "@id": "https://openebench.bsc.es/monitor/metrics/perl-extutils-cbuilder",
        "@license": "https://creativecommons.org/licenses/by/4.0/",
        "@nmsp": null,
        "@timestamp": "2021-04-08T03:06:07.315057Z",
        "@type": "metrics",
        "project": {
            "build": {},
            "deployment": {},
            "publications": [],
            "summary": {
                "description": true
            },
            "website": {
                "access_time": 95,
                "bioschemas": false,
                "copyright": false,
                "half_year_stat": [
                    {
                        "days": 181,
                        "serie": [
                            181
                        ],
                        "status": 200
                    }
                ],
                "https": true,
                "last_check": "2021-04-08T03:06:07.271088Z",
                "last_month_access": {
                    "average_access_time": 624,
                    "downtime_days": 0,
                    "uptime_days": 30
                },
                "license": false,
                "operational": 200,
                "redirects": [
                    {
                        "status": 301,
                        "url": "https://metacpan.org/release/ExtUtils-CBuilder"
                    }
                ],
                "ssl": true,
                "ssl_err": null
            }
        }
    }
]