[
    {
        "@id": "https://openebench.bsc.es/monitor/metrics/arraycluster",
        "@license": "https://creativecommons.org/licenses/by/4.0/",
        "@nmsp": null,
        "@timestamp": "2021-05-22T01:05:46.402089Z",
        "@type": "metrics",
        "project": {
            "build": {},
            "deployment": {},
            "publications": [],
            "summary": {
                "description": true
            },
            "website": {
                "access_time": 2669,
                "bioschemas": false,
                "copyright": false,
                "half_year_stat": [
                    {
                        "days": 180,
                        "serie": [
                            180
                        ],
                        "status": 200
                    }
                ],
                "https": true,
                "last_check": "2021-05-22T01:05:46.327318Z",
                "last_month_access": {
                    "average_access_time": 2009,
                    "downtime_days": 0,
                    "uptime_days": 29
                },
                "license": false,
                "operational": 200,
                "redirects": [
                    {
                        "status": 301,
                        "url": "https://www.ism.ac.jp/~higuchi/arraycluster.htm"
                    }
                ],
                "ssl": true,
                "ssl_err": null
            }
        }
    },
    {
        "@id": "https://openebench.bsc.es/monitor/metrics/biotools:arraycluster:1.0/app/www.ism.ac.jp",
        "@license": "https://creativecommons.org/licenses/by/4.0/",
        "@nmsp": "biotools",
        "@timestamp": "2021-05-22T01:05:46.518581Z",
        "@type": "metrics",
        "distribution": {
            "sourcecode": {
                "interpreted": true
            }
        },
        "project": {
            "build": {},
            "deployment": {},
            "documentation": {
                "manual": true
            },
            "publications": [
                {
                    "entries": [
                        {
                            "cit_count": 6,
                            "citations": [
                                {
                                    "count": 1,
                                    "year": "2009"
                                },
                                {
                                    "count": 2,
                                    "year": "2010"
                                },
                                {
                                    "count": 1,
                                    "year": "2011"
                                },
                                {
                                    "count": 1,
                                    "year": "2012"
                                },
                                {
                                    "count": 1,
                                    "year": "2013"
                                }
                            ],
                            "doi": "10.1093/bioinformatics/btl129",
                            "pmid": "16606685",
                            "ref_count": 2,
                            "refs": [
                                {
                                    "count": 1,
                                    "year": "1999"
                                },
                                {
                                    "count": 1,
                                    "year": "2002"
                                }
                            ],
                            "title": "ArrayCluster: an analytic tool for clustering, data visualization and module finder on gene expression profiles.",
                            "year": 2006
                        }
                    ]
                }
            ],
            "summary": {
                "description": true
            },
            "website": {
                "access_time": 1616,
                "bioschemas": false,
                "copyright": false,
                "half_year_stat": [
                    {
                        "days": 180,
                        "serie": [
                            180
                        ],
                        "status": 200
                    }
                ],
                "https": true,
                "last_check": "2021-05-22T01:05:46.450892Z",
                "last_month_access": {
                    "average_access_time": 792,
                    "downtime_days": 0,
                    "uptime_days": 29
                },
                "license": false,
                "operational": 200,
                "redirects": [
                    {
                        "status": 301,
                        "url": "https://www.ism.ac.jp/~higuchi/arraycluster.htm"
                    }
                ],
                "ssl": true,
                "ssl_err": null
            }
        },
        "support": {
            "email": false
        }
    }
]