[
    {
        "@id": "https://openebench.bsc.es/monitor/metrics/bioconda:qusage:2.10.0/cmd/bioconductor.org",
        "@license": "https://creativecommons.org/licenses/by/4.0/",
        "@nmsp": "bioconda",
        "@timestamp": "2021-11-06T07:32:22.895311Z",
        "@type": "metrics",
        "distribution": {
            "packages": true,
            "sourcecode": {}
        },
        "project": {
            "build": {},
            "deployment": {},
            "license": {
                "open_source": false,
                "osi": false
            },
            "publications": [],
            "summary": {
                "description": true
            },
            "website": {
                "access_time": 127,
                "bioschemas": false,
                "copyright": false,
                "half_year_stat": [
                    {
                        "days": 183,
                        "serie": [
                            183
                        ],
                        "status": 200
                    }
                ],
                "https": false,
                "last_check": "2021-04-25T03:23:11.986862Z",
                "last_month_access": {
                    "average_access_time": 149,
                    "downtime_days": 0,
                    "uptime_days": 1
                },
                "license": false,
                "operational": 200,
                "ssl": null,
                "ssl_err": null
            }
        }
    },
    {
        "@id": "https://openebench.bsc.es/monitor/metrics/bioconda:qusage:2.14.0/cmd/bioconductor.org",
        "@license": "https://creativecommons.org/licenses/by/4.0/",
        "@nmsp": "bioconda",
        "@timestamp": "2021-11-06T07:31:47.972648Z",
        "@type": "metrics",
        "distribution": {
            "packages": true,
            "sourcecode": {}
        },
        "project": {
            "build": {},
            "deployment": {},
            "license": {
                "open_source": false,
                "osi": false
            },
            "publications": [],
            "summary": {
                "description": true
            },
            "website": {
                "access_time": 260,
                "bioschemas": false,
                "copyright": false,
                "half_year_stat": [
                    {
                        "days": 183,
                        "serie": [
                            183
                        ],
                        "status": 200
                    }
                ],
                "https": false,
                "last_check": "2021-11-06T07:31:47.877371Z",
                "last_month_access": {
                    "average_access_time": 1365,
                    "downtime_days": 0,
                    "uptime_days": 30
                },
                "license": false,
                "operational": 200,
                "ssl": null,
                "ssl_err": null
            }
        }
    },
    {
        "@id": "https://openebench.bsc.es/monitor/metrics/bioconda:qusage:2.12.0/cmd/bioconductor.org",
        "@license": "https://creativecommons.org/licenses/by/4.0/",
        "@nmsp": "bioconda",
        "@timestamp": "2021-11-06T07:31:50.244010Z",
        "@type": "metrics",
        "distribution": {
            "packages": true,
            "sourcecode": {}
        },
        "project": {
            "build": {},
            "deployment": {},
            "license": {
                "open_source": false,
                "osi": false
            },
            "publications": [],
            "summary": {
                "description": true
            },
            "website": {
                "access_time": 132,
                "bioschemas": false,
                "copyright": false,
                "half_year_stat": [
                    {
                        "days": 183,
                        "serie": [
                            183
                        ],
                        "status": 200
                    }
                ],
                "https": false,
                "last_check": "2021-04-25T03:22:52.816459Z",
                "last_month_access": {
                    "average_access_time": 152,
                    "downtime_days": 0,
                    "uptime_days": 1
                },
                "license": false,
                "operational": 200,
                "ssl": null,
                "ssl_err": null
            }
        }
    },
    {
        "@id": "https://openebench.bsc.es/monitor/metrics/biotools:qusage:2.6.0/cmd/bioconductor.org",
        "@license": "https://creativecommons.org/licenses/by/4.0/",
        "@nmsp": "biotools",
        "@timestamp": "2021-11-06T07:32:30.352276Z",
        "@type": "metrics",
        "distribution": {
            "sourcecode": {
                "interpreted": true
            }
        },
        "project": {
            "build": {},
            "deployment": {},
            "documentation": {
                "manual": true
            },
            "license": {
                "open_source": true,
                "osi": true
            },
            "publications": [
                {
                    "entries": [
                        {
                            "cit_count": 77,
                            "citations": [
                                {
                                    "count": 3,
                                    "year": "2014"
                                },
                                {
                                    "count": 8,
                                    "year": "2015"
                                },
                                {
                                    "count": 7,
                                    "year": "2016"
                                },
                                {
                                    "count": 13,
                                    "year": "2017"
                                },
                                {
                                    "count": 6,
                                    "year": "2018"
                                },
                                {
                                    "count": 11,
                                    "year": "2019"
                                },
                                {
                                    "count": 15,
                                    "year": "2020"
                                },
                                {
                                    "count": 14,
                                    "year": "2021"
                                }
                            ],
                            "doi": "10.1093/nar/gkt660",
                            "pmcid": "PMC3794608",
                            "pmid": "23921631",
                            "ref_count": 41,
                            "refs": [
                                {
                                    "count": 1,
                                    "year": "1947"
                                },
                                {
                                    "count": 1,
                                    "year": "1975"
                                },
                                {
                                    "count": 1,
                                    "year": "2000"
                                },
                                {
                                    "count": 1,
                                    "year": "2001"
                                },
                                {
                                    "count": 1,
                                    "year": "2003"
                                },
                                {
                                    "count": 3,
                                    "year": "2005"
                                },
                                {
                                    "count": 6,
                                    "year": "2007"
                                },
                                {
                                    "count": 4,
                                    "year": "2008"
                                },
                                {
                                    "count": 6,
                                    "year": "2009"
                                },
                                {
                                    "count": 5,
                                    "year": "2010"
                                },
                                {
                                    "count": 5,
                                    "year": "2011"
                                },
                                {
                                    "count": 4,
                                    "year": "2012"
                                },
                                {
                                    "count": 2,
                                    "year": "2013"
                                },
                                {
                                    "count": 1,
                                    "year": "2016"
                                }
                            ],
                            "title": "Quantitative set analysis for gene expression: a method to quantify gene set differential expression including gene-gene correlations.",
                            "year": 2013
                        }
                    ]
                }
            ],
            "summary": {
                "description": true
            },
            "website": {
                "access_time": 673,
                "bioschemas": false,
                "copyright": false,
                "half_year_stat": [
                    {
                        "days": 183,
                        "serie": [
                            183
                        ],
                        "status": 200
                    }
                ],
                "https": false,
                "last_check": "2021-04-25T03:23:20.005063Z",
                "last_month_access": {
                    "average_access_time": 848,
                    "downtime_days": 0,
                    "uptime_days": 1
                },
                "license": false,
                "operational": 200,
                "ssl": null,
                "ssl_err": null
            }
        },
        "support": {
            "email": true
        }
    },
    {
        "@id": "https://openebench.bsc.es/monitor/metrics/biotools:qusage:2.6.0/lib/bioconductor.org",
        "@license": "https://creativecommons.org/licenses/by/4.0/",
        "@nmsp": "biotools",
        "@timestamp": "2021-11-06T07:31:52.358361Z",
        "@type": "metrics",
        "distribution": {
            "sourcecode": {
                "interpreted": true
            }
        },
        "project": {
            "build": {},
            "deployment": {},
            "documentation": {
                "manual": true
            },
            "license": {
                "open_source": true,
                "osi": true
            },
            "publications": [
                {
                    "entries": [
                        {
                            "cit_count": 77,
                            "citations": [
                                {
                                    "count": 3,
                                    "year": "2014"
                                },
                                {
                                    "count": 8,
                                    "year": "2015"
                                },
                                {
                                    "count": 7,
                                    "year": "2016"
                                },
                                {
                                    "count": 13,
                                    "year": "2017"
                                },
                                {
                                    "count": 6,
                                    "year": "2018"
                                },
                                {
                                    "count": 11,
                                    "year": "2019"
                                },
                                {
                                    "count": 15,
                                    "year": "2020"
                                },
                                {
                                    "count": 14,
                                    "year": "2021"
                                }
                            ],
                            "doi": "10.1093/nar/gkt660",
                            "pmcid": "PMC3794608",
                            "pmid": "23921631",
                            "ref_count": 41,
                            "refs": [
                                {
                                    "count": 1,
                                    "year": "1947"
                                },
                                {
                                    "count": 1,
                                    "year": "1975"
                                },
                                {
                                    "count": 1,
                                    "year": "2000"
                                },
                                {
                                    "count": 1,
                                    "year": "2001"
                                },
                                {
                                    "count": 1,
                                    "year": "2003"
                                },
                                {
                                    "count": 3,
                                    "year": "2005"
                                },
                                {
                                    "count": 6,
                                    "year": "2007"
                                },
                                {
                                    "count": 4,
                                    "year": "2008"
                                },
                                {
                                    "count": 6,
                                    "year": "2009"
                                },
                                {
                                    "count": 5,
                                    "year": "2010"
                                },
                                {
                                    "count": 5,
                                    "year": "2011"
                                },
                                {
                                    "count": 4,
                                    "year": "2012"
                                },
                                {
                                    "count": 2,
                                    "year": "2013"
                                },
                                {
                                    "count": 1,
                                    "year": "2016"
                                }
                            ],
                            "title": "Quantitative set analysis for gene expression: a method to quantify gene set differential expression including gene-gene correlations.",
                            "year": 2013
                        }
                    ]
                }
            ],
            "summary": {
                "description": true
            },
            "website": {
                "access_time": 673,
                "bioschemas": false,
                "copyright": false,
                "half_year_stat": [
                    {
                        "days": 183,
                        "serie": [
                            183
                        ],
                        "status": 200
                    }
                ],
                "https": false,
                "last_check": "2021-10-11T06:12:51.024767Z",
                "last_month_access": {
                    "average_access_time": 848,
                    "downtime_days": 0,
                    "uptime_days": 1
                },
                "license": false,
                "operational": 200,
                "ssl": null,
                "ssl_err": null
            }
        },
        "support": {
            "email": true
        }
    },
    {
        "@id": "https://openebench.bsc.es/monitor/metrics/qusage",
        "@license": "https://creativecommons.org/licenses/by/4.0/",
        "@nmsp": null,
        "@timestamp": "2021-11-06T07:30:19.871031Z",
        "@type": "metrics",
        "project": {
            "build": {},
            "deployment": {},
            "publications": [],
            "summary": {
                "description": true
            },
            "website": {
                "access_time": 673,
                "bioschemas": false,
                "copyright": false,
                "half_year_stat": [
                    {
                        "days": 183,
                        "serie": [
                            183
                        ],
                        "status": 200
                    }
                ],
                "https": false,
                "last_check": "2021-11-06T07:30:19.792699Z",
                "last_month_access": {
                    "average_access_time": 1308,
                    "downtime_days": 0,
                    "uptime_days": 30
                },
                "license": false,
                "operational": 200,
                "ssl": null,
                "ssl_err": null
            }
        }
    },
    {
        "@id": "https://openebench.bsc.es/monitor/metrics/bioconda:qusage:2.22.0/cmd/bioconductor.org",
        "@license": "https://creativecommons.org/licenses/by/4.0/",
        "@nmsp": "bioconda",
        "@timestamp": "2021-11-06T09:49:54.589078Z",
        "@type": "metrics",
        "distribution": {
            "packages": true,
            "sourcecode": {}
        },
        "project": {
            "build": {},
            "deployment": {},
            "license": {
                "open_source": false,
                "osi": false
            },
            "publications": [],
            "summary": {
                "description": true
            },
            "website": {
                "access_time": 337,
                "bioschemas": false,
                "copyright": false,
                "half_year_stat": [
                    {
                        "days": 156,
                        "serie": [
                            156
                        ],
                        "status": 200
                    }
                ],
                "https": true,
                "last_check": "2021-11-06T09:49:54.558771Z",
                "last_month_access": {
                    "average_access_time": 1361,
                    "downtime_days": 0,
                    "uptime_days": 30
                },
                "license": false,
                "operational": 200,
                "ssl": true,
                "ssl_err": null
            }
        }
    },
    {
        "@id": "https://openebench.bsc.es/monitor/metrics/bioconda:qusage:2.20.0/cmd/bioconductor.org",
        "@license": "https://creativecommons.org/licenses/by/4.0/",
        "@nmsp": "bioconda",
        "@timestamp": "2021-11-06T09:50:08.795289Z",
        "@type": "metrics",
        "distribution": {
            "packages": true,
            "sourcecode": {}
        },
        "project": {
            "build": {},
            "deployment": {},
            "license": {
                "open_source": false,
                "osi": false
            },
            "publications": [],
            "summary": {
                "description": true
            },
            "website": {
                "access_time": 336,
                "bioschemas": false,
                "copyright": false,
                "half_year_stat": [
                    {
                        "days": 156,
                        "serie": [
                            156
                        ],
                        "status": 200
                    }
                ],
                "https": true,
                "last_check": "2021-11-06T09:50:08.771031Z",
                "last_month_access": {
                    "average_access_time": 1303,
                    "downtime_days": 0,
                    "uptime_days": 30
                },
                "license": false,
                "operational": 200,
                "ssl": true,
                "ssl_err": null
            }
        }
    },
    {
        "@id": "https://openebench.bsc.es/monitor/metrics/bioconda:qusage:2.18.0/cmd/bioconductor.org",
        "@license": "https://creativecommons.org/licenses/by/4.0/",
        "@nmsp": "bioconda",
        "@timestamp": "2021-11-06T09:51:02.438065Z",
        "@type": "metrics",
        "distribution": {
            "packages": true,
            "sourcecode": {}
        },
        "project": {
            "build": {},
            "deployment": {},
            "license": {
                "open_source": false,
                "osi": false
            },
            "publications": [],
            "summary": {
                "description": true
            },
            "website": {
                "access_time": 466,
                "bioschemas": false,
                "copyright": false,
                "half_year_stat": [
                    {
                        "days": 155,
                        "serie": [
                            130,
                            25
                        ],
                        "status": 200
                    },
                    {
                        "days": 1,
                        "serie": [
                            1
                        ],
                        "status": 504
                    }
                ],
                "https": true,
                "last_check": "2021-11-06T09:51:02.411614Z",
                "last_month_access": {
                    "average_access_time": 169,
                    "downtime_days": 1,
                    "uptime_days": 29
                },
                "license": false,
                "operational": 200,
                "ssl": true,
                "ssl_err": null
            }
        }
    },
    {
        "@id": "https://openebench.bsc.es/monitor/metrics/bioconda:qusage:2.16.0/cmd/bioconductor.org",
        "@license": "https://creativecommons.org/licenses/by/4.0/",
        "@nmsp": "bioconda",
        "@timestamp": "2021-11-06T09:51:23.282929Z",
        "@type": "metrics",
        "distribution": {
            "packages": true,
            "sourcecode": {}
        },
        "project": {
            "build": {},
            "deployment": {},
            "license": {
                "open_source": false,
                "osi": false
            },
            "publications": [],
            "summary": {
                "description": true
            },
            "website": {
                "access_time": 392,
                "bioschemas": false,
                "copyright": false,
                "half_year_stat": [
                    {
                        "days": 155,
                        "serie": [
                            130,
                            25
                        ],
                        "status": 200
                    },
                    {
                        "days": 1,
                        "serie": [
                            1
                        ],
                        "status": 504
                    }
                ],
                "https": true,
                "last_check": "2021-11-06T09:51:23.245302Z",
                "last_month_access": {
                    "average_access_time": 157,
                    "downtime_days": 1,
                    "uptime_days": 29
                },
                "license": false,
                "operational": 200,
                "ssl": true,
                "ssl_err": null
            }
        }
    },
    {
        "@id": "https://openebench.bsc.es/monitor/metrics/bioconda:qusage:2.16.1/cmd/bioconductor.org",
        "@license": "https://creativecommons.org/licenses/by/4.0/",
        "@nmsp": "bioconda",
        "@timestamp": "2021-11-06T09:51:23.283049Z",
        "@type": "metrics",
        "distribution": {
            "packages": true,
            "sourcecode": {}
        },
        "project": {
            "build": {},
            "deployment": {},
            "license": {
                "open_source": false,
                "osi": false
            },
            "publications": [],
            "summary": {
                "description": true
            },
            "website": {
                "access_time": 273,
                "bioschemas": false,
                "copyright": false,
                "half_year_stat": [
                    {
                        "days": 155,
                        "serie": [
                            130,
                            25
                        ],
                        "status": 200
                    },
                    {
                        "days": 1,
                        "serie": [
                            1
                        ],
                        "status": 504
                    }
                ],
                "https": true,
                "last_check": "2021-11-06T09:51:23.243851Z",
                "last_month_access": {
                    "average_access_time": 110,
                    "downtime_days": 0,
                    "uptime_days": 25
                },
                "license": false,
                "operational": 200,
                "ssl": true,
                "ssl_err": null
            }
        }
    },
    {
        "@id": "https://openebench.bsc.es/monitor/metrics/bioconda:qusage:2.24.0/cmd/bioconductor.org",
        "@license": "https://creativecommons.org/licenses/by/4.0/",
        "@nmsp": "bioconda",
        "@timestamp": "2021-11-06T09:55:11.311714Z",
        "@type": "metrics",
        "distribution": {
            "packages": true,
            "sourcecode": {}
        },
        "project": {
            "build": {},
            "deployment": {},
            "license": {
                "open_source": false,
                "osi": false
            },
            "publications": [],
            "summary": {
                "description": true
            },
            "website": {
                "access_time": 344,
                "bioschemas": false,
                "copyright": false,
                "half_year_stat": [
                    {
                        "days": 156,
                        "serie": [
                            156
                        ],
                        "status": 200
                    }
                ],
                "https": true,
                "last_check": "2021-11-06T09:55:11.292613Z",
                "last_month_access": {
                    "average_access_time": 155,
                    "downtime_days": 0,
                    "uptime_days": 30
                },
                "license": false,
                "operational": 200,
                "ssl": true,
                "ssl_err": null
            }
        }
    },
    {
        "@id": "https://openebench.bsc.es/monitor/metrics/bioconda:qusage:2.26.0/cmd/bioconductor.org",
        "@license": "https://creativecommons.org/licenses/by/4.0/",
        "@nmsp": "bioconda",
        "@timestamp": "2021-11-06T09:55:23.421273Z",
        "@type": "metrics",
        "distribution": {
            "packages": true,
            "sourcecode": {}
        },
        "project": {
            "build": {},
            "deployment": {},
            "license": {
                "open_source": false,
                "osi": false
            },
            "publications": [],
            "summary": {
                "description": true
            },
            "website": {
                "access_time": 156,
                "bioschemas": false,
                "copyright": false,
                "half_year_stat": [
                    {
                        "days": 156,
                        "serie": [
                            156
                        ],
                        "status": 200
                    }
                ],
                "https": true,
                "last_check": "2021-11-06T09:55:23.402144Z",
                "last_month_access": {
                    "average_access_time": 162,
                    "downtime_days": 0,
                    "uptime_days": 30
                },
                "license": false,
                "operational": 200,
                "ssl": true,
                "ssl_err": null
            }
        }
    }
]