[
    {
        "@id": "https://openebench.bsc.es/monitor/metrics/bioconda:bioconductor-arrayexpress:1.38.0/cmd/bioconductor.org",
        "@license": "https://creativecommons.org/licenses/by/4.0/",
        "@nmsp": "bioconda",
        "@timestamp": "2022-05-21T01:30:06.417679Z",
        "@type": "metrics",
        "distribution": {
            "packages": true,
            "sourcecode": {}
        },
        "project": {
            "build": {},
            "deployment": {},
            "license": {
                "open_source": true,
                "osi": true
            },
            "publications": [],
            "summary": {
                "description": true
            },
            "website": {
                "access_time": 150,
                "bioschemas": false,
                "copyright": false,
                "half_year_stat": [
                    {
                        "days": 180,
                        "serie": [
                            180
                        ],
                        "status": 200
                    }
                ],
                "https": false,
                "last_check": "2022-05-21T01:30:06.356519Z",
                "last_month_access": {
                    "average_access_time": 172,
                    "downtime_days": 0,
                    "uptime_days": 29
                },
                "license": false,
                "operational": 200,
                "ssl": null,
                "ssl_err": null
            }
        },
        "vetoed": true
    },
    {
        "@id": "https://openebench.bsc.es/monitor/metrics/bioconda:bioconductor-arrayexpress:1.36.1/cmd/www.bioconductor.org",
        "@license": "https://creativecommons.org/licenses/by/4.0/",
        "@nmsp": "bioconda",
        "@timestamp": "2022-05-21T01:28:04.426271Z",
        "@type": "metrics",
        "distribution": {
            "packages": true,
            "sourcecode": {}
        },
        "project": {
            "build": {},
            "deployment": {},
            "license": {
                "open_source": true,
                "osi": true
            },
            "publications": [],
            "summary": {
                "description": true
            },
            "website": {
                "access_time": 453,
                "bioschemas": false,
                "copyright": false,
                "half_year_stat": [
                    {
                        "days": 180,
                        "serie": [
                            180
                        ],
                        "status": 200
                    }
                ],
                "https": true,
                "last_check": "2022-05-21T01:28:04.361964Z",
                "last_month_access": {
                    "average_access_time": 562,
                    "downtime_days": 0,
                    "uptime_days": 29
                },
                "license": false,
                "operational": 200,
                "ssl": true,
                "ssl_err": null
            }
        },
        "vetoed": true
    },
    {
        "@id": "https://openebench.bsc.es/monitor/metrics/bioconda:bioconductor-arrayexpress:1.40.0/cmd/bioconductor.org",
        "@license": "https://creativecommons.org/licenses/by/4.0/",
        "@nmsp": "bioconda",
        "@timestamp": "2022-05-21T01:28:06.905195Z",
        "@type": "metrics",
        "distribution": {
            "packages": true,
            "sourcecode": {}
        },
        "project": {
            "build": {},
            "deployment": {},
            "license": {
                "open_source": true,
                "osi": true
            },
            "publications": [],
            "summary": {
                "description": true
            },
            "website": {
                "access_time": 149,
                "bioschemas": false,
                "copyright": false,
                "half_year_stat": [
                    {
                        "days": 180,
                        "serie": [
                            180
                        ],
                        "status": 200
                    }
                ],
                "https": false,
                "last_check": "2022-05-21T01:28:06.842261Z",
                "last_month_access": {
                    "average_access_time": 147,
                    "downtime_days": 0,
                    "uptime_days": 29
                },
                "license": false,
                "operational": 200,
                "ssl": null,
                "ssl_err": null
            }
        },
        "vetoed": true
    },
    {
        "@id": "https://openebench.bsc.es/monitor/metrics/bioconductor-arrayexpress",
        "@license": "https://creativecommons.org/licenses/by/4.0/",
        "@nmsp": null,
        "@timestamp": "2022-05-21T01:30:16.377551Z",
        "@type": "metrics",
        "project": {
            "build": {},
            "deployment": {},
            "publications": [],
            "summary": {
                "description": true
            },
            "website": {
                "access_time": 453,
                "bioschemas": false,
                "copyright": false,
                "half_year_stat": [
                    {
                        "days": 180,
                        "serie": [
                            180
                        ],
                        "status": 200
                    }
                ],
                "https": true,
                "last_check": "2022-05-21T01:28:04.361964Z",
                "last_month_access": {
                    "average_access_time": 497,
                    "downtime_days": 0,
                    "uptime_days": 29
                },
                "license": false,
                "operational": 200,
                "ssl": true,
                "ssl_err": null
            }
        },
        "vetoed": true
    },
    {
        "@id": "https://openebench.bsc.es/monitor/metrics/bioconda:bioconductor-arrayexpress:1.50.0/cmd/bioconductor.org",
        "@license": "https://creativecommons.org/licenses/by/4.0/",
        "@nmsp": "bioconda",
        "@timestamp": "2022-05-21T08:57:06.361819Z",
        "@type": "metrics",
        "distribution": {
            "packages": true,
            "sourcecode": {}
        },
        "project": {
            "build": {},
            "deployment": {},
            "license": {
                "open_source": true,
                "osi": true
            },
            "publications": [],
            "summary": {
                "description": true
            },
            "website": {
                "access_time": 151,
                "bioschemas": false,
                "copyright": false,
                "half_year_stat": [
                    {
                        "days": 180,
                        "serie": [
                            180
                        ],
                        "status": 200
                    }
                ],
                "https": true,
                "last_check": "2022-05-21T08:57:06.3236Z",
                "last_month_access": {
                    "average_access_time": 154,
                    "downtime_days": 0,
                    "uptime_days": 29
                },
                "license": false,
                "operational": 200,
                "ssl": true,
                "ssl_err": null
            }
        },
        "vetoed": true
    },
    {
        "@id": "https://openebench.bsc.es/monitor/metrics/bioconda:bioconductor-arrayexpress:1.46.0/cmd/bioconductor.org",
        "@license": "https://creativecommons.org/licenses/by/4.0/",
        "@nmsp": "bioconda",
        "@timestamp": "2022-05-21T09:02:00.098056Z",
        "@type": "metrics",
        "distribution": {
            "packages": true,
            "sourcecode": {}
        },
        "project": {
            "build": {},
            "deployment": {},
            "license": {
                "open_source": true,
                "osi": true
            },
            "publications": [],
            "summary": {
                "description": true
            },
            "website": {
                "access_time": 160,
                "bioschemas": false,
                "copyright": false,
                "half_year_stat": [
                    {
                        "days": 180,
                        "serie": [
                            180
                        ],
                        "status": 200
                    }
                ],
                "https": true,
                "last_check": "2022-05-21T09:02:00.046592Z",
                "last_month_access": {
                    "average_access_time": 180,
                    "downtime_days": 0,
                    "uptime_days": 29
                },
                "license": false,
                "operational": 200,
                "ssl": true,
                "ssl_err": null
            }
        },
        "vetoed": true
    },
    {
        "@id": "https://openebench.bsc.es/monitor/metrics/bioconda:bioconductor-arrayexpress:1.48.0/cmd/bioconductor.org",
        "@license": "https://creativecommons.org/licenses/by/4.0/",
        "@nmsp": "bioconda",
        "@timestamp": "2022-05-21T09:02:17.773058Z",
        "@type": "metrics",
        "distribution": {
            "packages": true,
            "sourcecode": {}
        },
        "project": {
            "build": {},
            "deployment": {},
            "license": {
                "open_source": true,
                "osi": true
            },
            "publications": [],
            "summary": {
                "description": true
            },
            "website": {
                "access_time": 158,
                "bioschemas": false,
                "copyright": false,
                "half_year_stat": [
                    {
                        "days": 180,
                        "serie": [
                            180
                        ],
                        "status": 200
                    }
                ],
                "https": true,
                "last_check": "2022-05-21T09:02:17.738836Z",
                "last_month_access": {
                    "average_access_time": 147,
                    "downtime_days": 0,
                    "uptime_days": 29
                },
                "license": false,
                "operational": 200,
                "ssl": true,
                "ssl_err": null
            }
        },
        "vetoed": true
    },
    {
        "@id": "https://openebench.bsc.es/monitor/metrics/bioconda:bioconductor-arrayexpress:1.42.0/cmd/bioconductor.org",
        "@license": "https://creativecommons.org/licenses/by/4.0/",
        "@nmsp": "bioconda",
        "@timestamp": "2022-05-21T09:02:19.209816Z",
        "@type": "metrics",
        "distribution": {
            "packages": true,
            "sourcecode": {}
        },
        "project": {
            "build": {},
            "deployment": {},
            "license": {
                "open_source": true,
                "osi": true
            },
            "publications": [],
            "summary": {
                "description": true
            },
            "website": {
                "access_time": 145,
                "bioschemas": false,
                "copyright": false,
                "half_year_stat": [
                    {
                        "days": 180,
                        "serie": [
                            180
                        ],
                        "status": 200
                    }
                ],
                "https": true,
                "last_check": "2022-05-21T09:02:19.159527Z",
                "last_month_access": {
                    "average_access_time": 221,
                    "downtime_days": 0,
                    "uptime_days": 29
                },
                "license": false,
                "operational": 200,
                "ssl": true,
                "ssl_err": null
            }
        },
        "vetoed": true
    },
    {
        "@id": "https://openebench.bsc.es/monitor/metrics/bioconda:bioconductor-arrayexpress:1.44.0/cmd/bioconductor.org",
        "@license": "https://creativecommons.org/licenses/by/4.0/",
        "@nmsp": "bioconda",
        "@timestamp": "2022-05-21T09:02:27.553009Z",
        "@type": "metrics",
        "distribution": {
            "packages": true,
            "sourcecode": {}
        },
        "project": {
            "build": {},
            "deployment": {},
            "license": {
                "open_source": true,
                "osi": true
            },
            "publications": [],
            "summary": {
                "description": true
            },
            "website": {
                "access_time": 265,
                "bioschemas": false,
                "copyright": false,
                "half_year_stat": [
                    {
                        "days": 180,
                        "serie": [
                            180
                        ],
                        "status": 200
                    }
                ],
                "https": true,
                "last_check": "2022-05-21T09:02:27.487566Z",
                "last_month_access": {
                    "average_access_time": 211,
                    "downtime_days": 0,
                    "uptime_days": 29
                },
                "license": false,
                "operational": 200,
                "ssl": true,
                "ssl_err": null
            }
        },
        "vetoed": true
    },
    {
        "@id": "https://openebench.bsc.es/monitor/metrics/bioconda:bioconductor-arrayexpress:1.52.0/cmd/bioconductor.org",
        "@license": "https://creativecommons.org/licenses/by/4.0/",
        "@nmsp": "bioconda",
        "@timestamp": "2022-05-21T09:02:34.457337Z",
        "@type": "metrics",
        "distribution": {
            "packages": true,
            "sourcecode": {}
        },
        "project": {
            "build": {},
            "deployment": {},
            "license": {
                "open_source": true,
                "osi": true
            },
            "publications": [],
            "summary": {
                "description": true
            },
            "website": {
                "access_time": 261,
                "bioschemas": false,
                "copyright": false,
                "half_year_stat": [
                    {
                        "days": 180,
                        "serie": [
                            180
                        ],
                        "status": 200
                    }
                ],
                "https": true,
                "last_check": "2022-05-21T09:02:34.424634Z",
                "last_month_access": {
                    "average_access_time": 213,
                    "downtime_days": 0,
                    "uptime_days": 29
                },
                "license": false,
                "operational": 200,
                "ssl": true,
                "ssl_err": null
            }
        },
        "vetoed": true
    },
    {
        "@id": "https://openebench.bsc.es/monitor/metrics/bioconda:bioconductor-arrayexpress:1.54.0/cmd/bioconductor.org",
        "@license": "https://creativecommons.org/licenses/by/4.0/",
        "@nmsp": "bioconda",
        "@timestamp": "2022-05-21T09:14:01.997690Z",
        "@type": "metrics",
        "distribution": {
            "packages": true,
            "sourcecode": {}
        },
        "project": {
            "build": {},
            "deployment": {},
            "license": {
                "open_source": true,
                "osi": true
            },
            "publications": [],
            "summary": {
                "description": true
            },
            "website": {
                "access_time": 145,
                "bioschemas": false,
                "copyright": false,
                "half_year_stat": [
                    {
                        "days": 180,
                        "serie": [
                            180
                        ],
                        "status": 200
                    }
                ],
                "https": true,
                "last_check": "2022-05-21T09:14:01.967186Z",
                "last_month_access": {
                    "average_access_time": 162,
                    "downtime_days": 0,
                    "uptime_days": 29
                },
                "license": false,
                "operational": 200,
                "ssl": true,
                "ssl_err": null
            }
        },
        "vetoed": true
    }
]