[{"@timestamp": "2022-01-15T02:49:56.863198Z", "project": {"build": {}, "deployment": {}, "publications": [], "summary": {}, "website": {"access_time": 373, "bioschemas": false, "copyright": false, "https": true, "last_check": "2021-04-23T01:49:35.007817Z", "license": false, "operational": 200, "ssl": true, "last_month_access": {"average_access_time": 323, "downtime_days": 0, "uptime_days": 1}, "half_year_stat": [{"days": 183, "serie": [183], "status": 200}], "ssl_err": null, "redirects": [{"status": 301, "url": "https://tandem.bu.edu/trf/trf.html"}]}}, "@id": "https://openebench.bsc.es/monitor/metrics/boltons", "@nmsp": null, "@type": "metrics", "@license": "https://creativecommons.org/licenses/by/4.0/"}, {"@timestamp": "2022-01-15T13:25:07.959130Z", "distribution": {"packages": null, "sourcecode": {"repository": {"anonymous": null, "online": null}, "free": null, "interpreted": null, "license": null, "public": true, "readme": false}, "binaries": {"freeness": null, "registration": null}, "source_packages": false}, "project": {"build": {}, "deployment": {}, "publications": [], "summary": {}, "website": {"access_time": 373, "bioschemas": false, "copyright": false, "https": true, "last_check": "2021-04-23T01:49:35.261084Z", "license": false, "operational": 200, "ssl": true, "last_month_access": {"average_access_time": 323, "downtime_days": 0, "uptime_days": 1}, "half_year_stat": [{"days": 183, "serie": [183], "status": 200}], "ssl_err": null, "redirects": [{"status": 301, "url": "https://tandem.bu.edu/trf/trf.html"}]}, "readme": false}, "support": {"issue_tracking": {"public_tracker": null, "resolve_time": null}}, "@id": "https://openebench.bsc.es/monitor/metrics/bioconda:boltons:16.4.1/cmd/conda.anaconda.org", "@nmsp": "bioconda", "@type": "metrics", "@license": "https://creativecommons.org/licenses/by/4.0/"}]